manager/__init__.py
manager/__main__.py
manager/_version.py
manager/ai_service.py
manager/app.py
manager/icon_converter.py
manager/logic.py
manager/static/favicon.ico
manager/templates/index.html
win_folder_manager-1.1.0.dist-info/licenses/LICENSE
win_folder_manager-1.1.0.dist-info/METADATA
win_folder_manager-1.1.0.dist-info/WHEEL
win_folder_manager-1.1.0.dist-info/entry_points.txt
win_folder_manager-1.1.0.dist-info/top_level.txt
win_folder_manager-1.1.0.dist-info/RECORD
