Metadata-Version: 2.4
Name: win-folder-manager
Version: 1.1.0
Summary: A lightweight, Flask-powered web file manager for Windows. Manage, browse, and transfer files via a clean browser UI.
License: GPLv3
Classifier: License :: OSI Approved :: GNU General Public License v3 (GPLv3)
Classifier: Programming Language :: Python :: 3
Classifier: Operating System :: Microsoft :: Windows
Requires-Python: >=3.8
License-File: LICENSE
Requires-Dist: flask
Requires-Dist: pywin32
Requires-Dist: Pillow
Requires-Dist: requests
Dynamic: classifier
Dynamic: license
Dynamic: license-file
Dynamic: requires-dist
Dynamic: requires-python
Dynamic: summary
